CHANGELOG.txt
LICENSE.txt
MANIFEST.in
README.txt
setup.py
test.py
awesome calculator/__init__.py
awesome calculator/calculator.py
kalulatar.egg-info/PKG-INFO
kalulatar.egg-info/SOURCES.txt
kalulatar.egg-info/dependency_links.txt
kalulatar.egg-info/top_level.txt